{
    "animations": {
        "player": {
            "idle_up": {
                "curr_frame": 0,
                "frame_dur": 200,
                "frames": [{ "x": 0, "y": 64, "w": 16, "h": 32 }]
            },
            "idle_down": {
                "curr_frame": 0,
                "frame_dur": 200,
                "frames": [{ "x": 0, "y": 0, "w": 16, "h": 32 }]
            },
            "idle_left": {
                "curr_frame": 0,
                "frame_dur": 200,
                "frames": [{ "x": 0, "y": 96, "w": 16, "h": 32 }]
            },
            "idle_right": {
                "curr_frame": 0,
                "frame_dur": 200,
                "frames": [{ "x": 0, "y": 32, "w": 16, "h": 32 }]
            },
            "walk_up": {
                "curr_frame": 0,
                "frame_dur": 200,
                "frames": [
                    { "x": 0, "y": 64, "w": 16, "h": 32 },
                    { "x": 16, "y": 64, "w": 16, "h": 32 },
                    { "x": 32, "y": 64, "w": 16, "h": 32 },
                    { "x": 48, "y": 64, "w": 16, "h": 32 }
                ]
            },
            "walk_down": {
                "curr_frame": 0,
                "frame_dur": 200,
                "frames": [
                    { "x": 0, "y": 0, "w": 16, "h": 32 },
                    { "x": 16, "y": 0, "w": 16, "h": 32 },
                    { "x": 32, "y": 0, "w": 16, "h": 32 },
                    { "x": 48, "y": 0, "w": 16, "h": 32 }
                ]
            },
            "walk_left": {
                "curr_frame": 0,
                "frame_dur": 200,
                "frames": [
                    { "x": 0, "y": 96, "w": 16, "h": 32 },
                    { "x": 16, "y": 96, "w": 16, "h": 32 },
                    { "x": 32, "y": 96, "w": 16, "h": 32 },
                    { "x": 48, "y": 96, "w": 16, "h": 32 }
                ]
            },
            "walk_right": {
                "curr_frame": 0,
                "frame_dur": 200,
                "frames": [
                    { "x": 0, "y": 32, "w": 16, "h": 32 },
                    { "x": 16, "y": 32, "w": 16, "h": 32 },
                    { "x": 32, "y": 32, "w": 16, "h": 32 },
                    { "x": 48, "y": 32, "w": 16, "h": 32 }
                ]
            },
            "attack_up": {
                "curr_frame": 0,
                "frame_dur": 100,
                "frames": [
                    { "x": 8, "y": 160, "w": 16, "h": 32 },
                    { "x": 40, "y": 160, "w": 16, "h": 32 },
                    { "x": 72, "y": 160, "w": 16, "h": 32 },
                    { "x": 104, "y": 160, "w": 16, "h": 32 }
                ]
            },
            "attack_down": {
                "curr_frame": 0,
                "frame_dur": 100,
                "frames": [
                    { "x": 8, "y": 128, "w": 16, "h": 32 },
                    { "x": 40, "y": 128, "w": 16, "h": 32 },
                    { "x": 72, "y": 128, "w": 16, "h": 32 },
                    { "x": 104, "y": 128, "w": 16, "h": 32 }
                ]
            },
            "attack_left": {
                "curr_frame": 0,
                "frame_dur": 100,
                "frames": [
                    { "x": 0, "y": 224, "w": 32, "h": 32 },
                    { "x": 32, "y": 224, "w": 32, "h": 32 },
                    { "x": 64, "y": 224, "w": 32, "h": 32 },
                    { "x": 96, "y": 224, "w": 32, "h": 32 }
                ]
            },
            "attack_right": {
                "curr_frame": 0,
                "frame_dur": 100,
                "frames": [
                    { "x": 0, "y": 192, "w": 32, "h": 32 },
                    { "x": 32, "y": 192, "w": 32, "h": 32 },
                    { "x": 64, "y": 192, "w": 32, "h": 32 },
                    { "x": 96, "y": 192, "w": 32, "h": 32 }
                ]
            }
        },
        "enemy": {
            "idle": {
                "curr_frame": 0,
                "frame_dur": 200,
                "frames": [
                    { "x": 128, "y": 0, "w": 32, "h": 32 },
                    { "x": 128, "y": 32, "w": 32, "h": 32 },
                    { "x": 128, "y": 64, "w": 32, "h": 32 },
                    { "x": 128, "y": 96, "w": 32, "h": 32 }
                ]
            },
            "walk": {
                "curr_frame": 0,
                "frame_dur": 200,
                "frames": [
                    { "x": 0, "y": 0, "w": 32, "h": 32 },
                    { "x": 32, "y": 0, "w": 32, "h": 32 },
                    { "x": 64, "y": 0, "w": 32, "h": 32 },
                    { "x": 96, "y": 0, "w": 32, "h": 32 }
                ]
            }
        },
        "comsumable": {
            "health": {
                "curr_frame": 0,
                "frame_dur": 200,
                "frames": [
                    { "x": 0, "y": 48, "w": 16, "h": 16 },
                    { "x": 16, "y": 48, "w": 16, "h": 16 },
                    { "x": 32, "y": 48, "w": 16, "h": 16 },
                    { "x": 48, "y": 48, "w": 16, "h": 16 }
                ]
            },
            "power": {
                "curr_frame": 0,
                "frame_dur": 200,
                "frames": [
                    { "x": 0, "y": 64, "w": 16, "h": 16 },
                    { "x": 16, "y": 64, "w": 16, "h": 16 },
                    { "x": 32, "y": 64, "w": 16, "h": 16 },
                    { "x": 48, "y": 64, "w": 16, "h": 16 }
                ]
            }
        },
        "heart": {
            "damaged": {
                "curr_frame": 0,
                "frame_dur": 200,
                "frames": [
                    { "x": 64, "y": 0, "w": 16, "h": 16 },
                    { "x": 80, "y": 0, "w": 16, "h": 16 },
                    { "x": 96, "y": 0, "w": 16, "h": 16 },
                    { "x": 112, "y": 0, "w": 16, "h": 16 },
                    { "x": 128, "y": 0, "w": 16, "h": 16 }
                ]
            }
        }
    },
    "sprites": {
        "number": {
            "1": { "x": 80, "y": 224, "w": 16, "h": 16 },
            "2": { "x": 96, "y": 224, "w": 16, "h": 16 },
            "3": { "x": 112, "y": 224, "w": 16, "h": 16 },
            "4": { "x": 128, "y": 224, "w": 16, "h": 16 },
            "5": { "x": 80, "y": 240, "w": 16, "h": 16 },
            "6": { "x": 96, "y": 240, "w": 16, "h": 16 },
            "7": { "x": 112, "y": 240, "w": 16, "h": 16 },
            "8": { "x": 128, "y": 240, "w": 16, "h": 16 },
            "9": { "x": 80, "y": 256, "w": 16, "h": 16 },
            "0": { "x": 96, "y": 256, "w": 16, "h": 16 }
        },
        "heart": {
            "0": { "x": 64, "y": 0, "w": 16, "h": 16 },
            "1": { "x": 80, "y": 0, "w": 16, "h": 16 },
            "2": { "x": 96, "y": 0, "w": 16, "h": 16 },
            "3": { "x": 112, "y": 0, "w": 16, "h": 16 },
            "4": { "x": 128, "y": 0, "w": 16, "h": 16 }
        },
        "container": { "x": 0, "y": 224, "w": 80, "h": 64 }
    }
}